Workbook

Sheet general
A1: campo | B1: valor
A2: nombre | B2: Banco Davivienda SA
A3: sector | B3: Financiero
A4: ticker | B4: PFDAVVNDA
A5: moneda | B5: COP
A6: país | B6: Colombia
A7: logo | B7: davivienda-logo.png

Sheet kpis
A1: kpi | B1: valor
A2: net_income | B2: =+trimestres!B2 -> 268584000000
A3: roe | B3: =+trimestres!B3 -> 0.016307298
A4: roa | B4: =+trimestres!B4 -> 0.0017955446
A5: solvency | B5: =+trimestres!B5 -> 0.10605217
A6: loan_portfolio | B6: =+trimestres!B6 -> 101525475000000
A7: npl | B7: =+trimestres!B7 -> 0
A8: deposits | B8: =+trimestres!B8 -> 139652798000000
A9: nim | B9: =+trimestres!B9 -> 0.011908831

Sheet trimestres
A1: metric | B1: Q1 2025 | C1: Q2 2025 | D1: Q3 2025 | E1: Q4 2025
A2: net_income | B2: 268584000000 | C2: 430124000000 | D2: 393286000000
A3: roe | B3: 0.016307298 | C3: 0.025325507 | D3: 0.022519994
A4: roa | B4: 0.0017955446 | C4: 0.0028097934 | D4: 0.0025236244
A5: solvency | B5: =+resultados!B17/resultados!B18 -> 0.10605217 | C5: =+resultados!C17/resultados!C18 -> 0.097544311 | D5: =+resultados!D17/resultados!D18 -> 0.10074793
A6: loan_portfolio | B6: 101525475000000 | C6: 102184055000000 | D6: 104791203000000
A7: npl | B7: =+resultados!B6/resultados!B5 -> 0 | C7: =+resultados!C6/resultados!C5 -> 0 | D7: =+resultados!D6/resultados!D5 -> 0
A8: deposits | B8: =+resultados!B4 -> 139652798000000 | C8: =+resultados!C4 -> 139940054000000 | D8: =+resultados!D4 -> 139515157000000
A9: nim | B9: =+resultados!B9/resultados!B19 -> 0.011908831 | C9: =+resultados!C9/resultados!C19 -> 0.013628937 | D9: =+resultados!D9/resultados!D19 -> 0.013731387

Sheet resultados
A1: metric | B1: Q1 2025 | C1: Q2 2025 | D1: Q3 2025 | E1: Q4 2025
A2: assets | B2: 189875020000000 | C2: 189549748000000 | D2: 190467909000000
A3: equity | B3: 16154329000000 | C3: 16411664000000 | D3: 16683651000000
A4: deposits | B4: 139652798000000 | C4: 139940054000000 | D4: 139515157000000
A5: loan_portfolio | B5: 138088352000000 | C5: 139493678000000 | D5: 138809895000000
A6: cartera vencida
A7: income_interest | B7: 4887529000000 | C7: 4882100000000 | D7: 4872360000000
A8: paid_interest | B8: 2617692000000 | C8: 2563345000000 | D8: 2529871000000
A9: margin_interest | B9: =+B7-B8 -> 2269837000000 | C9: =+C7-C8 -> 2318755000000 | D9: =+D7-D8 -> 2342489000000
A10: operational_costs | B10: 1611752000000 | C10: 1594416000000 | D10: 1630816000000
A11: margin_interest-operational_costs | B11: =+B9-B10 -> 658085000000 | C11: =+C9-C10 -> 724339000000 | D11: =+D9-D10 -> 711673000000
A12: net_income | B12: 290594000000 | C12: 433669000000 | D12: 373601000000
A13: margin_interest/assets | B13: =+B9/B2 -> 0.011954374 | C13: =+C9/C2 -> 0.012232963 | D13: =+D9/D2 -> 0.012298602
A14: operational_costs/margin_interest | B14: =+B10/B9 -> 0.7100739 | C14: =+C10/C9 -> 0.68761728 | D14: =+D10/D9 -> 0.6961894
A15: loans/deposits | B15: =+B5/B4 -> 0.9887976 | C15: =+C5/C4 -> 0.99681023 | D15: =+D5/D4 -> 0.99494491
A16: equity/assets | B16: =+B3/B2 -> 0.085078748 | C16: =+C3/C2 -> 0.086582357 | D16: =+D3/D2 -> 0.087592976
A17: technical_equity | B17: 15946180000000 | C17: 16206766000000 | D17: 16476950000000
A18: APNR | B18: 150361653800000 | C18: 166147731000000 | D18: =138803895000000+1998405000000+17158341000000+4655258000000+930383000000 -> 163546282000000
A19: average_assets | B19: =+(191327286000000+B2)/2 -> 190601153000000 | C19: =+(150719627000000+C2)/2 -> 170134687500000 | D19: =+(150719627000000+D2)/2 -> 170593768000000

Sheet patrimonio_tecnico
A1: metric | B1: Q1 2025 | C1: Q2 2025 | D1: Q3 2025 | E1: Q4 2025
A2: capital_pagado | B2: 3553000000 | C2: -
A3: reserva_legal | B3: 4009803000000 | C3: -
A4: utilidades_retenidas | B4: -269924000000 | C4: -
A5: prima_colocacion | B5: 6781641000000 | C5: -
A6: intereses_minoritarios | B6: 58938000000 | C6: -
A7: ajustes_regulacion | B7: 7731000000 | C7: -
A9: bonos | B9: 19025955000000
A10: provisiones | B10: 41769000000
B12: =SUM(B2:B7) -> 10591742000000
B14: 4706623000000
B15: 536556000000
B16: 368131000000
B17: =+B12+B14+B15+B16 -> 16203052000000
B19: 16411234000000

Sheet cartera
